triade/__init__.py
triade/cli.py
triade/errors.py
triade/lib.py
triade/thesaurus.py
triade/xml_lib.py
triade-0.4.0.dist-info/METADATA
triade-0.4.0.dist-info/WHEEL
triade-0.4.0.dist-info/entry_points.txt
triade-0.4.0.dist-info/licenses/LICENSE
triade-0.4.0.dist-info/RECORD
