Metadata-Version: 2.1
Name: triade
Version: 0.4.0
Project-URL: Homepage, https://github.com/llucasls/triade
Author-email: "Lucas L. S. Haine" <lucaslshaine@gmail.com>
License-File: LICENSE
Classifier: License :: OSI Approved :: MIT License
Classifier: Operating System :: POSIX
Classifier: Programming Language :: Python :: 3
Requires-Python: >=3.7
Requires-Dist: pyyaml
Requires-Dist: toml
